License.txt
README.md
setup.py
crypper/__init__.py
crypper/permutations.py
crypper.egg-info/PKG-INFO
crypper.egg-info/SOURCES.txt
crypper.egg-info/dependency_links.txt
crypper.egg-info/top_level.txt