Metadata-Version: 2.1
Name: crypper
Version: 0.2
Summary: permutations required for aes and des
Author: TMS
License: MIT
Platform: UNKNOWN
License-File: License.txt
